gyver/__init__.py
gyver/misc/__init__.py
gyver/misc/asynciter.py
gyver/misc/autodiscovery/__init__.py
gyver/misc/autodiscovery/base.py
gyver/misc/autodiscovery/runtime.py
gyver/misc/autodiscovery/static.py
gyver/misc/casting.py
gyver/misc/enums.py
gyver/misc/exc.py
gyver/misc/functions.py
gyver/misc/json.py
gyver/misc/namespace.py
gyver/misc/sequences.py
gyver/misc/strings.py
gyver/misc/timezone.py
gyver/misc/worker.py
gyver_misc-0.5.12.dist-info/LICENSE
gyver_misc-0.5.12.dist-info/METADATA
gyver_misc-0.5.12.dist-info/WHEEL
gyver_misc-0.5.12.dist-info/RECORD
