Metadata-Version: 2.3
Name: gyver-misc
Version: 0.5.12
Summary: 
Author: Gustavo Cardoso
Author-email: self.gustavocorrea@gmail.com
Requires-Python: >=3.10,<4.0
Classifier: Programming Language :: Python :: 3
Classifier: Programming Language :: Python :: 3.10
Classifier: Programming Language :: Python :: 3.11
Classifier: Programming Language :: Python :: 3.12
Classifier: Programming Language :: Python :: 3.13
Requires-Dist: exceptiongroup (>=1.2.1,<2.0.0)
Requires-Dist: orjson (>=3.10.5,<4.0.0)
Requires-Dist: typing-extensions (>=4.12.2,<5.0.0)
